Workbook

Sheet Upload
A1: =IF(DB!A1="","",DB!A1) -> 商品コード | B1: =IF(DB!B1="","",DB!B1) -> 商品名 | C1: =IF(DB!C1="","",DB!C1) -> メーカー | D1: =IF(DB!D1="","",DB!D1) -> 標準原価 | E1: 設定モード | F1: =IF(DB!F1="","",DB!F1) -> 納期区分 | G1: A | H1: B | I1: C | J1: D | K1: E | L1: F | M1: G | N1: P
A2: =IF(DB!A2="","",DB!A2) | B2: =IF(DB!B2="","",DB!B2) -> RICOH SP ﾄﾅ- 8400 | C2: =IF(DB!C2="","",DB!C2) -> RICOH | D2: =IF(DB!D2="","",DB!D2) | E2: =IF(DB!E2="","",DB!E2) -> 自動 | F2: =IF(DB!F2="","",DB!F2) | G2: =IF(DB!G2="","",DB!G2) -> 44754 | H2: =IF(DB!H2="","",DB!H2) -> 44754 | ... J2: =IF(DB!J2="","",DB!J2)
A3: =IF(DB!A3="","",DB!A3) | B3: =IF(DB!B3="","",DB!B3) -> RICOH SP ﾄﾞﾗﾑﾕﾆﾂﾄ 8400 | C3: =IF(DB!C3="","",DB!C3) -> RICOH | D3: =IF(DB!D3="","",DB!D3) | E3: =IF(DB!E3="","",DB!E3) -> 自動 | F3: =IF(DB!F3="","",DB!F3) | G3: =IF(DB!G3="","",DB!G3) -> 32270 | H3: =IF(DB!H3="","",DB!H3) -> 32270 | ... J3: =IF(DB!J3="","",DB!J3)
A4: =IF(DB!A4="","",DB!A4) | B4: =IF(DB!B4="","",DB!B4) -> IPSIO SPﾄﾅ- 8200 | C4: =IF(DB!C4="","",DB!C4) -> RICOH | D4: =IF(DB!D4="","",DB!D4) | E4: =IF(DB!E4="","",DB!E4) -> 自動 | F4: =IF(DB!F4="","",DB!F4) | G4: =IF(DB!G4="","",DB!G4) -> 32513 | H4: =IF(DB!H4="","",DB!H4) -> 32513 | ... J4: =IF(DB!J4="","",DB!J4)
A5: =IF(DB!A5="","",DB!A5) | B5: =IF(DB!B5="","",DB!B5) -> ｲﾌﾟｼｵ SP ﾄﾞﾗﾑﾕﾆﾂﾄ 8300 | C5: =IF(DB!C5="","",DB!C5) -> RICOH | D5: =IF(DB!D5="","",DB!D5) | E5: =IF(DB!E5="","",DB!E5) -> 自動 | F5: =IF(DB!F5="","",DB!F5) | G5: =IF(DB!G5="","",DB!G5) -> 32270 | H5: =IF(DB!H5="","",DB!H5) -> 32270 | ... J5: =IF(DB!J5="","",DB!J5)
A6: =IF(DB!A6="","",DB!A6) | B6: =IF(DB!B6="","",DB!B6) -> IPSIO SP ﾄﾞﾗﾑﾕﾆﾂﾄ 8200 | C6: =IF(DB!C6="","",DB!C6) -> RICOH | D6: =IF(DB!D6="","",DB!D6) | E6: =IF(DB!E6="","",DB!E6) -> 自動 | F6: =IF(DB!F6="","",DB!F6) | G6: =IF(DB!G6="","",DB!G6) -> 32513 | H6: =IF(DB!H6="","",DB!H6) -> 32513 | ... J6: =IF(DB!J6="","",DB!J6)
A7: =IF(DB!A7="","",DB!A7) | B7: =IF(DB!B7="","",DB!B7) -> RICOH SP ﾄﾅ- 6400 | C7: =IF(DB!C7="","",DB!C7) -> RICOH | D7: =IF(DB!D7="","",DB!D7) | E7: =IF(DB!E7="","",DB!E7) -> 自動 | F7: =IF(DB!F7="","",DB!F7) | G7: =IF(DB!G7="","",DB!G7) -> 14453 | H7: =IF(DB!H7="","",DB!H7) -> 14453 | ... J7: =IF(DB!J7="","",DB!J7)
A8: =IF(DB!A8="","",DB!A8) | B8: =IF(DB!B8="","",DB!B8) -> RICOH SP ﾄﾅ- 6400H | C8: =IF(DB!C8="","",DB!C8) -> RICOH | D8: =IF(DB!D8="","",DB!D8) | E8: =IF(DB!E8="","",DB!E8) -> 自動 | F8: =IF(DB!F8="","",DB!F8) | G8: =IF(DB!G8="","",DB!G8) -> 22261 | H8: =IF(DB!H8="","",DB!H8) -> 22261 | ... J8: =IF(DB!J8="","",DB!J8)
A9: =IF(DB!A9="","",DB!A9) | B9: =IF(DB!B9="","",DB!B9) -> RICOH SP ﾄﾞﾗﾑﾕﾆﾂﾄ 6400 | C9: =IF(DB!C9="","",DB!C9) -> RICOH | D9: =IF(DB!D9="","",DB!D9) | E9: =IF(DB!E9="","",DB!E9) -> 自動 | F9: =IF(DB!F9="","",DB!F9) | G9: =IF(DB!G9="","",DB!G9) -> 9163 | H9: =IF(DB!H9="","",DB!H9) -> 9094 | ... J9: =IF(DB!J9="","",DB!J9)
A10: =IF(DB!A10="","",DB!A10) | B10: =IF(DB!B10="","",DB!B10) -> IPSIO SP ﾄﾅ-ｶ-ﾄﾘﾂｼﾞ6100 | C10: =IF(DB!C10="","",DB!C10) -> RICOH | D10: =IF(DB!D10="","",DB!D10) | E10: =IF(DB!E10="","",DB!E10) -> 自動 | F10: =IF(DB!F10="","",DB!F10) | G10: =IF(DB!G10="","",DB!G10) -> 24236 | H10: =IF(DB!H10="","",DB!H10) -> 23871 | ... J10: =IF(DB!J10="","",DB!J10)
A11: =IF(DB!A11="","",DB!A11) | B11: =IF(DB!B11="","",DB!B11) -> IPSIO SP ﾄﾅ-ｶ-ﾄﾘﾂｼﾞ6100H | C11: =IF(DB!C11="","",DB!C11) -> RICOH | D11: =IF(DB!D11="","",DB!D11) | E11: =IF(DB!E11="","",DB!E11) -> 自動 | F11: =IF(DB!F11="","",DB!F11) | G11: =IF(DB!G11="","",DB!G11) -> 48472 | H11: =IF(DB!H11="","",DB!H11) -> 47742 | ... J11: =IF(DB!J11="","",DB!J11)
A12: =IF(DB!A12="","",DB!A12) | B12: =IF(DB!B12="","",DB!B12) -> IPSIO SP ECﾄﾅ-ｶ-ﾄﾘﾂｼﾞ 6100 | C12: =IF(DB!C12="","",DB!C12) -> RICOH | D12: =IF(DB!D12="","",DB!D12) | E12: =IF(DB!E12="","",DB!E12) -> 自動 | F12: =IF(DB!F12="","",DB!F12) | G12: =IF(DB!G12="","",DB!G12) -> 21912 | H12: =IF(DB!H12="","",DB!H12) -> 21417 | ... J12: =IF(DB!J12="","",DB!J12)
A13: =IF(DB!A13="","",DB!A13) | B13: =IF(DB!B13="","",DB!B13) -> IPSIO SP ECﾄﾅ-ｶ-ﾄﾘﾂｼﾞ 6100H | C13: =IF(DB!C13="","",DB!C13) -> RICOH | D13: =IF(DB!D13="","",DB!D13) | E13: =IF(DB!E13="","",DB!E13) -> 自動 | F13: =IF(DB!F13="","",DB!F13) | G13: =IF(DB!G13="","",DB!G13) -> 43558 | H13: =IF(DB!H13="","",DB!H13) -> 42574 | ... J13: =IF(DB!J13="","",DB!J13)
... A9285: =IF(DB!A9285="","",DB!A9285) | B9285: =IF(DB!B9285="","",DB!B9285) | C9285: =IF(DB!C9285="","",DB!C9285) | D9285: =IF(DB!D9285="","",DB!D9285) | E9285: =IF(DB!E9285="","",DB!E9285) | F9285: =IF(DB!F9285="","",DB!F9285) | G9285: =IF(DB!G9285="","",DB!G9285) | H9285: =IF(DB!H9285="","",DB!H9285) | ... J9285: =IF(DB!J9285="","",DB!J9285)

Sheet DB
A1: 商品コード | B1: 商品名 | C1: メーカー | D1: 標準原価 | E1: 設定モード | F1: 納期区分 | G1: パターン1 | H1: パターン2 | I1: パターン3 | J1: パターン4 | K1: 商品コード | L1: 商品名 | M1: 仕様 | N1: 定価
B2: RICOH SP ﾄﾅ- 8400 | C2: RICOH | E2: 自動 | G2: 44754 | H2: 44754 | K2: 0000 | L2: フリー | M2: 純正
B3: RICOH SP ﾄﾞﾗﾑﾕﾆﾂﾄ 8400 | C3: RICOH | E3: 自動 | G3: 32270 | H3: 32270 | K3: 00000014 | L3: EPSON A3モノクロページプリンター LP-S3250
B4: IPSIO SPﾄﾅ- 8200 | C4: RICOH | E4: 自動 | G4: 32513 | H4: 32513 | K4: 00000015 | L4: アクリルパーテーション 60X60 窓付き 4枚ｾｯﾄ
B5: ｲﾌﾟｼｵ SP ﾄﾞﾗﾑﾕﾆﾂﾄ 8300 | C5: RICOH | E5: 自動 | G5: 32270 | H5: 32270 | K5: 00000016 | L5: EPSON A4ｶﾗｰｲﾝｸｼﾞｪｯﾄ PX-S740
B6: IPSIO SP ﾄﾞﾗﾑﾕﾆﾂﾄ 8200 | C6: RICOH | E6: 自動 | G6: 32513 | H6: 32513 | K6: 315253 | L6: RICOH PPCｽﾃｰﾌﾟﾗｰ針 ﾀｲﾌﾟN 5000針×2個/箱 315253 | M6: 純正 | N6: 3200
B7: RICOH SP ﾄﾅ- 6400 | C7: RICOH | E7: 自動 | G7: 14453 | H7: 14453 | K7: 319167 | L7: RICOH PPCｽﾃｰﾌﾟﾗｰ ｶｰﾄﾘｯｼﾞ ﾀｲﾌﾟV 5000 319167 3251638 | M7: 純正 | N7: 2400
B8: RICOH SP ﾄﾅ- 6400H | C8: RICOH | E8: 自動 | G8: 22261 | H8: 22261 | K8: 3410SD | L8: 富士ﾌｲﾙﾑ ﾚｰｻﾞｰﾌﾟﾘﾝﾀｰ ApeosPort Print 3410SD (NL300086) | M8: 純正
B9: RICOH SP ﾄﾞﾗﾑﾕﾆﾂﾄ 6400 | C9: RICOH | E9: 自動 | G9: 9163 | H9: 9094 | K9: 3ED28A | L9: HP712B ｲﾝｸｶｰﾄﾘｯｼﾞ 3ED28A ﾌﾞﾗｯｸ 38ml | M9: 純正 | N9: 4100
B10: IPSIO SP ﾄﾅ-ｶ-ﾄﾘﾂｼﾞ6100 | C10: RICOH | E10: 自動 | G10: 24236 | H10: 23871 | K10: 3ED67A | L10: HP712 ｲﾝｸｶｰﾄﾘｯｼﾞ 3ED67A ｼｱﾝ 29ml | M10: 純正 | N10: 3400
B11: IPSIO SP ﾄﾅ-ｶ-ﾄﾘﾂｼﾞ6100H | C11: RICOH | E11: 自動 | G11: 48472 | H11: 47742 | K11: 3ED68A | L11: HP712 ｲﾝｸｶｰﾄﾘｯｼﾞ 3ED68A ﾏｾﾞﾝﾀ 29ml | M11: 純正 | N11: 3400
B12: IPSIO SP ECﾄﾅ-ｶ-ﾄﾘﾂｼﾞ 6100 | C12: RICOH | E12: 自動 | G12: 21912 | H12: 21417 | K12: 3ED69A | L12: HP712 ｲﾝｸｶｰﾄﾘｯｼﾞ 3ED69A ｲｴﾛｰ 29ml | M12: 純正 | N12: 3400
B13: IPSIO SP ECﾄﾅ-ｶ-ﾄﾘﾂｼﾞ 6100H | C13: RICOH | E13: 自動 | G13: 43558 | H13: 42574 | K13: 4020SD | L13: 富士ﾌｲﾙﾑ ﾚｰｻﾞｰﾌﾟﾘﾝﾀｰ ApeosPort Print 4020SD (NL300085) | M13: 純正
B14: RICOH ドラムユニット P6000 | C14: RICOH | E14: 自動 | G14: 9163 | H14: 9163 | K14: 51645AA | L14: HP45 ﾌﾟﾘﾝﾄｶｰﾄﾘｯｼﾞ 黒 51645AA#003 | M14: 純正
B15: RICOH SP ﾄﾅ- 4500L | C15: RICOH | E15: 自動 | G15: 8898 | H15: 8898 | K15: 527F9A | L15: HP LaserJet ﾄﾅｰｺﾚｸｼｮﾝﾕﾆｯﾄ 527F9A | M15: 純正 | N15: 9145
B16: RICOH SP ﾄﾅ- 4500 | C16: RICOH | E16: 自動 | G16: 14323 | H16: 14323 | K16: 527G0A | L16: HP LJ ﾌｭｰｻﾞｰｷｯﾄ 527G0A | M16: 純正 | N16: 62682
B17: RICOH SP ﾄﾅ- 4500H | C17: RICOH | E17: 自動 | G17: 22432 | H17: 22432 | K17: 527G2A | L17: HP LaserJet ｴﾝﾊﾝｽﾌｭｰｻﾞｰｷｯﾄ 527G2A | M17: 純正 | N17: 102609
B18: RICOH SP ﾄﾞﾗﾑﾕﾆﾂﾄ 4500 | C18: RICOH | E18: 自動 | G18: 7481 | H18: 7481 | K18: 527G6A | L18: HP LJ ｴﾝﾊﾝｽﾌｭｰｻﾞｰｷｯﾄ 527G6A | M18: 純正 | N18: 70191
B19: IPSIO SP ﾄﾅ-ｶ-ﾄﾘﾂｼﾞ4200 | C19: RICOH | E19: 自動 | G19: 21647 | H19: 21647 | K19: 527G9A | L19: HP LJ ｲﾒｰｼﾞﾄﾗﾝｽﾌｧｰﾍﾞﾙﾄｷｯﾄ 527G9A | M19: 純正 | N19: 87682
B20: IPSIO SP ﾄﾅ-ｶ-ﾄﾘﾂｼﾞ4200H | C20: RICOH | E20: 自動 | G20: 34662 | H20: 34662 | K20: 527H2A | L20: HP LJ ﾄﾚｲﾛｰﾗｰｷｯﾄ(ﾄﾚｲ2用) 527H2A | M20: 純正 | N20: 9273
B21: IPSIO SP ECﾄﾅ-ｶ-ﾄﾘﾂｼﾞ 4200 | C21: RICOH | E21: 自動 | G21: 19405 | H21: 19405 | K21: 527H3A | L21: HP LJ ﾄﾚｲﾛｰﾗｰｷｯﾄ(ﾄﾚｲ1用) 527H3A | M21: 純正 | N21: 9345
B22: IPSIO SP ECﾄﾅ-ｶ-ﾄﾘﾂｼﾞ 4200H | C22: RICOH | E22: 自動 | G22: 30957 | H22: 30957 | K22: 6H122A | L22: HP LaserJet ADFﾒﾝﾃﾅﾝｽｷｯﾄ 6H122A | M22: 純正 | N22: 13064
B23: RICOH トナー P 500L | C23: RICOH | E23: 自動 | G23: 9098 | H23: 9098 | K23: B432dnw | L23: OKI ﾚｰｻﾞｰﾌﾟﾘﾝﾀｰ B432dnw
B24: RICOH トナー P 500 | C24: RICOH | E24: 自動 | G24: 24338 | H24: 24338 | K24: B6Y01A | L24: HP HP771B ｲﾝｸｶｰﾄﾘｯｼﾞ ﾏｾﾞﾝﾀ B6Y01A | M24: 純正 | N24: 41900
B25: RICOH トナー P 500H | C25: RICOH | E25: 自動 | G25: 32061 | H25: 32061 | K25: B6Y03A | L25: HP HP771B ｲﾝｸｶｰﾄﾘｯｼﾞ ﾗｲﾄﾏｾﾞﾝﾀ B6Y03A | M25: 純正 | N25: 41900
B26: RICOH ドラムユニット P 500 | C26: RICOH | E26: 自動 | G26: 11576 | H26: 11576 | K26: B6Y04A | L26: HP HP771B ｲﾝｸｶｰﾄﾘｯｼﾞ ﾗｲﾄｼｱﾝ B6Y04A | M26: 純正 | N26: 41900
B27: RICOH SP ﾄﾅ-ｶ-ﾄﾘﾂｼﾞ3700 | C27: RICOH | E27: 自動 | G27: 11641 | H27: 11641 | K27: B822dn | L27: OKI ﾚｰｻﾞｰﾌﾟﾘﾝﾀｰ B822dn | N27: 128000
B28: RICOH SP ﾄﾅ-ｶ-ﾄﾘﾂｼﾞ3700H | C28: RICOH | E28: 自動 | G28: 19162 | H28: 19162 | K28: B842dn | L28: OKI ﾚｰｻﾞｰﾌﾟﾘﾝﾀｰ B842dn | N28: 168000
B29: IPSIO SP ﾄﾅ-ｶ-ﾄﾘﾂｼﾞ 3400 | C29: RICOH | E29: 自動 | G29: 7426 | H29: 7426 | K29: B842dnt | L29: OKI ﾚｰｻﾞｰﾌﾟﾘﾝﾀｰ B842dnt | N29: 198000
B30: IPSIO SP ﾄﾅ-ｶ-ﾄﾘﾂｼﾞ 3400H | C30: RICOH | E30: 自動 | G30: 13240 | H30: 13240 | K30: BPTL700 | L30: SHARP BPTL700 一次転写ｸﾘｰﾅｰﾌﾞﾚｰﾄﾞ | M30: 純正
B31: IPSIO SP ECﾄﾅ-ｶ-ﾄﾘﾂｼﾞ 3400H | C31: RICOH | E31: 自動 | G31: 11812 | H31: 11812 | K31: C1P70A | L31: ADF ﾛｰﾗｰｷｯﾄ C1P70A | M31: 純正 | N31: 14882
B32: RICOH SP ﾄﾅ-ｶ-ﾄﾘﾂｼﾞ2300 | C32: RICOH | E32: 自動 | G32: 6690 | H32: 6690 | K32: C2410SD | L32: 富士ﾌｲﾙﾑ ﾚｰｻﾞｰﾌﾟﾘﾝﾀｰ ApeosPort Print C2410SD (NC100608) | M32: 純正
B33: RICOH SP ﾄﾅ-ｶ-ﾄﾘﾂｼﾞ2300H | C33: RICOH | E33: 自動 | G33: 13734 | H33: 13734 | K33: C4570 | L33: 富士ﾌｲﾙﾑ ﾚｰｻﾞｰﾌﾟﾘﾝﾀｰ ApeosPrint C4570 (NC100646) | M33: 純正 | N33: 442000
B34: RICOH SP ﾄﾅ-ｶ-ﾄﾘﾂｼﾞ2100 | C34: RICOH | E34: 自動 | G34: 6690 | H34: 6690 | K34: C650dnw | L34: OKI ﾚｰｻﾞｰﾌﾟﾘﾝﾀｰ C650dnw | N34: 178000
B35: RICOH SP ﾄﾅ-ｶ-ﾄﾘﾂｼﾞ2100H | C35: RICOH | E35: 自動 | G35: 13839 | H35: 13839 | K35: C6656AA | L35: -終息- HP56ﾌﾟﾘﾝﾄｶｰﾄﾘｯｼﾞ 黒 C6656AA#003 | M35: 純正
B36: RICOH SP ﾄﾅ- ｼｱﾝ C840 | C36: RICOH | E36: 自動 | G36: 17394 | H36: 17394 | K36: C7977A | L36: HP LTO7 Ultrium 15TB RW ﾃﾞｰﾀｶｰﾄﾘｯｼﾞ C7977A | M36: 純正 | N36: 32000
B37: RICOH SP ﾄﾅ- ﾏｾﾞﾝﾀ C840 | C37: RICOH | E37: 自動 | G37: 17394 | H37: 17394 | K37: C811dn | L37: OKI COREFIDO C811dn | M37: 純正
B38: RICOH SP ﾄﾅ- ｲｴﾛ- C840 | C38: RICOH | E38: 自動 | G38: 17394 | H38: 17394 | K38: C824dn | L38: OKI ﾚｰｻﾞｰﾌﾟﾘﾝﾀｰ C824dn
B39: RICOH SP ﾄﾅ- ﾌﾞﾗﾂｸ C840 | C39: RICOH | E39: 自動 | G39: 17729 | H39: 17729 | K39: C835dnw | L39: OKI ﾚｰｻﾞｰｶﾗｰﾌﾟﾘﾝﾀｰ C835dnw | N39: 178000
B40: RICOH SP ﾄﾅ- ｼｱﾝ C840H | C40: RICOH | E40: 自動 | G40: 26749 | H40: 26749 | K40: C844dnw | L40: OKI ﾚｰｻﾞｰｶﾗｰﾌﾟﾘﾝﾀｰ C844dnw | N40: 248000
B41: RICOH SP ﾄﾅ- ﾏｾﾞﾝﾀ C840H | C41: RICOH | E41: 自動 | G41: 26749 | H41: 26749 | K41: C8766HJ | L41: HP135 ﾌﾟﾘﾝﾄｶｰﾄﾘｯｼﾞ ｶﾗｰ C8766HJ | M41: 純正 | N41: 3500
B42: RICOH SP ﾄﾅ- ｲｴﾛ- C840H | C42: RICOH | E42: 自動 | G42: 26749 | H42: 26749 | K42: C911dn | L42: OKI ﾚｰｻﾞｰﾌﾟﾘﾝﾀｰ C911dn | N42: 498000
B43: RICOH SP ﾄﾅ- ﾌﾞﾗﾂｸ C840H | C43: RICOH | E43: 自動 | G43: 28187 | H43: 28187 | K43: C931dn | L43: OKI ﾚｰｻﾞｰﾌﾟﾘﾝﾀｰ C931dn | N43: 898000
B44: RICOH SP ﾄﾞﾗﾑﾕﾆﾂﾄｶﾗ- C840 | C44: RICOH | E44: 自動 | G44: 57104 | H44: 57104 | K44: C9364HJ | L44: -終息-HP HP129 ﾌﾟﾘﾝﾄｶｰﾄﾘｯｼﾞ 黒 C9364HJ | M44: 純正
B45: RICOH SP ﾄﾞﾗﾑﾕﾆﾂﾄﾌﾞﾗﾂｸ C840 | C45: RICOH | E45: 自動 | G45: 19854 | H45: 19854 | K45: C941dn | L45: OKI ﾚｰｻﾞｰﾌﾟﾘﾝﾀｰ C941dn | N45: 1398000
B46: ｲﾌﾟｼｵ SP ﾄﾞﾗﾑﾕﾆﾂﾄ ﾌﾞﾗﾂｸ C830 | C46: RICOH | E46: 自動 | G46: 19854 | H46: 19854 | K46: C9730A | L46: HP ﾌﾟﾘﾝﾄｶｰﾄﾘｯｼﾞ C9730A 黒 | M46: 純正 | N46: 69736
B47: ｲﾌﾟｼｵ SP ﾄﾞﾗﾑﾕﾆﾂﾄ ｶﾗ- C830 | C47: RICOH | E47: 自動 | G47: 57104 | H47: 57104 | K47: C9731A | L47: HP ﾌﾟﾘﾝﾄｶｰﾄﾘｯｼﾞ C9731A ｼｱﾝ | M47: 純正 | N47: 97945
B48: RICOH SP ﾊｲﾄﾅ-ﾎﾞﾄﾙ C840 | C48: RICOH | E48: 自動 | G48: 1573 | H48: 1573 | K48: C9732A | L48: HP ﾌﾟﾘﾝﾄｶｰﾄﾘｯｼﾞ C9732A ｲｴﾛｰ | M48: 純正 | N48: 97945
B49: RICOH SP MEﾄﾅ- ｼｱﾝ C840 | C49: RICOH | E49: 自動 | G49: 17654 | H49: 17654 | K49: C9733A | L49: HP ﾌﾟﾘﾝﾄｶｰﾄﾘｯｼﾞ C9733A ﾏｾﾞﾝﾀ | M49: 純正 | N49: 97945
B50: RICOH SP MEﾄﾅ- ﾏｾﾞﾝﾀ C840 | C50: RICOH | E50: 自動 | G50: 17654 | H50: 17654 | K50: CAN | L50: ※CANON直送のため納期確認中
B51: RICOH SP MEﾄﾅ- ｲｴﾛ- C840 | C51: RICOH | E51: 自動 | G51: 17654 | H51: 17654 | K51: CB316HJ | L51: HP178 ｲﾝｸｶｰﾄﾘｯｼﾞ 黒 CB316HJ | M51: 純正 | N51: 1618
B52: RICOH SP MEﾄﾅ- ﾌﾞﾗﾂｸ C840 | C52: RICOH | E52: 自動 | G52: 19487 | H52: 19487 | K52: CB318HJ | L52: HP178 ｲﾝｸｶｰﾄﾘｯｼﾞ ｼｱﾝ CB318HJ | M52: 純正 | N52: 1509
B53: RICOH SP MEﾄﾅ- ｼｱﾝ C840H | C53: RICOH | E53: 自動 | G53: 32781 | H53: 32781 | K53: CB319HJ | L53: HP178 ｲﾝｸｶｰﾄﾘｯｼﾞ ﾏｾﾞﾝﾀ CB319HJ | M53: 純正 | N53: 1509
B54: RICOH SP MEﾄﾅ- ﾏｾﾞﾝﾀ C840H | C54: RICOH | E54: 自動 | G54: 32781 | H54: 32781 | K54: CB320HJ | L54: HP178 ｲﾝｸｶｰﾄﾘｯｼﾞ ｲｴﾛｰ CB320HJ | M54: 純正 | N54: 1509
B55: RICOH SP MEﾄﾅ- ｲｴﾛ- C840H | C55: RICOH | E55: 自動 | G55: 32781 | H55: 32781 | K55: CC640HJ | L55: HP HP121 ﾌﾟﾘﾝﾄｶｰﾄﾘｯｼﾞ 黒 CC640HJ | M55: 純正
B56: RICOH SP MEﾄﾅ- ﾌﾞﾗﾂｸ C840H | C56: RICOH | E56: 自動 | G56: 31109 | H56: 31109 | K56: CC643HJ | L56: HP HP121 ﾌﾟﾘﾝﾄｶｰﾄﾘｯｼﾞ 3色ｶﾗｰ CC643HJ | M56: 純正 | N56: 2036
B57: RICOH SP MEドラムユニット カラー C840 | C57: RICOH | E57: 自動 | G57: 57964 | H57: 57964 | K57: CE248A | L57: ADFﾒﾝﾃﾅﾝｽｷｯﾄ (CM4540) CE248A | M57: 純正 | N57: 16091
B58: RICOH SP MEドラムユニット ブラック C840 | C58: RICOH | E58: 自動 | G58: 20085 | H58: 20085 | K58: CE270A | L58: HP ﾌﾟﾘﾝﾄｶｰﾄﾘｯｼﾞ 黒 (CP5525) CE270A | M58: 純正 | N58: 58127
B59: IPSIO SP ﾄﾅ- ｼｱﾝ C830 | C59: RICOH | E59: 自動 | G59: 17394 | H59: 17394 | K59: CE271A | L59: HP ﾌﾟﾘﾝﾄｶｰﾄﾘｯｼﾞ CE271A ｼｱﾝ (CP5525) | M59: 純正 | N59: 87845
B60: IPSIO SP ﾄﾅ- ﾏｾﾞﾝﾀ C830 | C60: RICOH | E60: 自動 | G60: 17394 | H60: 17394 | K60: CE272A | L60: HP ﾌﾟﾘﾝﾄｶｰﾄﾘｯｼﾞ CE272A ｲｴﾛｰ (CP5525) | M60: 純正 | N60: 87845
B61: IPSIO SP ﾄﾅ- ｲｴﾛ- C830 | C61: RICOH | E61: 自動 | G61: 17394 | H61: 17394 | K61: CE273A | L61: HP ﾌﾟﾘﾝﾄｶｰﾄﾘｯｼﾞ CE273A ﾏｾﾞﾝﾀ (CP5525) | M61: 純正 | N61: 87845
B62: IPSIO SP ﾄﾅ- ﾌﾞﾗﾂｸ C830 | C62: RICOH | E62: 自動 | G62: 17729 | H62: 17729 | K62: CE340A | L62: HP 651A 黒 ﾄﾅｰｶｰﾄﾘｯｼﾞ CE340A | M62: 純正 | N62: 40473
B63: IPSIO SP ﾄﾅ- ｼｱﾝ C830H | C63: RICOH | E63: 自動 | G63: 26749 | H63: 26749 | K63: CE341A | L63: HP 651A ｼｱﾝ ﾄﾅｰｶｰﾄﾘｯｼﾞ CE341A | M63: 純正 | N63: 101991
B64: IPSIO SP ﾄﾅ- ﾏｾﾞﾝﾀ C830H | C64: RICOH | E64: 自動 | G64: 26749 | H64: 26749 | K64: CE342A | L64: HP 651A ｲｴﾛｰ ﾄﾅｰｶｰﾄﾘｯｼﾞ CE342A | M64: 純正 | N64: 101991
B65: IPSIO SP ﾄﾅ- ｲｴﾛ- C830H | C65: RICOH | E65: 自動 | G65: 26749 | H65: 26749 | K65: CE343A | L65: HP 651A ﾏｾﾞﾝﾀ ﾄﾅｰｶｰﾄﾘｯｼﾞ CE343A | M65: 純正 | N65: 101991
B66: IPSIO SP ﾄﾅ- ﾌﾞﾗﾂｸ C830H | C66: RICOH | E66: 自動 | G66: 28187 | H66: 28187 | K66: CE390X | L66: HP HP 90X ﾄﾅｰｶｰﾄﾘｯｼﾞ 黒 大容量 CE390X | M66: 純正 | N66: 63491
B67: ｲﾌﾟｼｵ SP ﾊｲﾄﾅ-ﾎﾞﾄﾙ C830 | C67: RICOH | E67: 自動 | G67: 1573 | H67: 1573 | K67: CF214A | L67: HP 14A ﾄﾅｰｶｰﾄﾘｯｼﾞ 黒 CF214A | M67: 純正 | N67: 47636
... B70: IPSIO SP ﾄﾅ- ｲｴﾛ- C820 | C70: RICOH | E70: 自動 | G70: 19419 | H70: 18990 | K70: CF287X | L70: HP HP 87X ﾄﾅｰｶｰﾄﾘｯｼﾞ 黒(大容量) CF287X | M70: 純正 | N70: 66364
B71: IPSIO SP ﾄﾅ- ﾌﾞﾗﾂｸ C820 | C71: RICOH | E71: 自動 | G71: 19827 | H71: 19389 | K71: CH562WA | L71: HP61 ｲﾝｸｶｰﾄﾘｯｼﾞ CH562WA ｶﾗｰ | M71: 純正
B72: SP ｶﾝｺｳﾀｲﾄﾞﾗﾑﾕﾆﾂﾄ ｶﾗ- C820 | C72: RICOH | E72: 自動 | G72: 42913 | H72: 42281 | K72: CH563WA | L72: HP HP61XL CH563WA ｲﾝｸｶｰﾄﾘｯｼﾞ 黒(増量) | M72: 純正
B73: SP ｶﾝｺｳﾀｲﾄﾞﾗﾑﾕﾆﾂﾄ ﾌﾞﾗﾂｸ C820 | C73: RICOH | E73: 自動 | G73: 14938 | H73: 14718 | K73: CH564WA | L73: HP HP61XL CH564WA ｲﾝｸｶｰﾄﾘｯｼﾞ ｶﾗｰ(増量) | M73: 純正
B74: IPSIO SP ﾄﾅ- ｼｱﾝ C820H | C74: RICOH | E74: 自動 | G74: 29430 | H74: 28980 | K74: CIB07CB | M74: 互換
B75: IPSIO SP ﾄﾅ- ﾏｾﾞﾝﾀ C820H | C75: RICOH | E75: 自動 | G75: 29430 | H75: 28980 | K75: CIB07CL4B | L75: -使用不可-互換 ｲﾝｸｶｰﾄﾘｯｼﾞ IB07CL4B 4色ｾｯﾄ | M75: 互換
B76: IPSIO SP ﾄﾅ- ｲｴﾛ- C820H | C76: RICOH | E76: 自動 | G76: 29430 | H76: 28980 | K76: CIB07KB | M76: 互換
B77: IPSIO SP ﾄﾅ- ﾌﾞﾗﾂｸ C820H | C77: RICOH | E77: 自動 | G77: 31065 | H77: 30590 | K77: CIB07MB | M77: 互換
B78: ｲﾌﾟｼｵ SP ﾊｲﾄﾅ-ﾎﾞﾄﾙ C810 | C78: RICOH | E78: 自動 | G78: 1698 | H78: 1710 | K78: CIB07YB | M78: 互換
B79: RICOH SP ﾄﾅ- ｼｱﾝ C740 | C79: RICOH | E79: 自動 | G79: 5553 | H79: 5553 | K79: CN045AA | L79: HP 950XL ｲﾝｸｶｰﾄﾘｯｼﾞ CN045AA 黒 (増量) | M79: 純正
B80: RICOH SP ﾄﾅ- ﾏｾﾞﾝﾀ C740 | C80: RICOH | E80: 自動 | G80: 5553 | H80: 5553 | K80: CN046AA | L80: HP 951XL ｲﾝｸｶｰﾄﾘｯｼﾞ CN046AA ｼｱﾝ | M80: 純正
B81: RICOH SP ﾄﾅ- ｲｴﾛ- C740 | C81: RICOH | E81: 自動 | G81: 5553 | H81: 5553 | K81: CN047AA | L81: HP 951XL ｲﾝｸｶｰﾄﾘｯｼﾞ CN047AA ﾏｾﾞﾝﾀ | M81: 純正
B82: RICOH SP ﾄﾅ- ﾌﾞﾗﾂｸ C740 | C82: RICOH | E82: 自動 | G82: 6289 | H82: 6289 | K82: CN048AA | L82: HP 951XL ｲﾝｸｶｰﾄﾘｯｼﾞ CN048AA ｲｴﾛｰ | M82: 純正
B83: RICOH SP ﾄﾅ- ｼｱﾝ C740H | C83: RICOH | E83: 自動 | G83: 10987 | H83: 10987 | K83: CN057AA | L83: HP932 ｲﾝｸｶｰﾄﾘｯｼﾞ 黒 CN057AA | M83: 純正 | N83: 3036
B84: RICOH SP ﾄﾅ- ﾏｾﾞﾝﾀ C740H | C84: RICOH | E84: 自動 | G84: 10987 | H84: 10987 | K84: CN684HJ | L84: HP178XL ｲﾝｸｶｰﾄﾘｯｼﾞ 黒 ｽﾘﾑ増量 CN684HJ | M84: 純正 | N84: 2773
B85: RICOH SP ﾄﾅ- ｲｴﾛ- C740H | C85: RICOH | E85: 自動 | G85: 10987 | H85: 10987 | K85: CR281AA | L85: HP178 ｲﾝｸｶｰﾄﾘｯｼﾞ 4色ﾏﾙﾁﾊﾟｯｸ CR281AA | M85: 純正
B86: RICOH SP ﾄﾅ- ﾌﾞﾗﾂｸ C740H | C86: RICOH | E86: 自動 | G86: 12295 | H86: 12295 | K86: D | L86: ※現在、出荷元の倉庫が逼迫しているため、回答納期より遅れが生じる可能性がございます。予めご容赦ください。
B87: RICOH SP ﾄﾞﾗﾑﾕﾆﾂﾄ ｶﾗ- C740 | C87: RICOH | E87: 自動 | G87: 36820 | H87: 36820 | K87: DR225W2 | L87: CANON ﾄﾞｷｭﾒﾝﾄｽｷｬﾅｰ DR-C225WⅡ 3259C001
B88: RICOH SP ﾄﾞﾗﾑﾕﾆﾂﾄ ﾌﾞﾗﾂｸ C740 | C88: RICOH | E88: 自動 | G88: 12295 | H88: 12295 | K88: DR290CL | L88: brother ﾄﾞﾗﾑﾕﾆｯﾄ DR-290CL | M88: 純正 | N88: 9450
B89: IPSIO SP ﾄﾅ- ｼｱﾝ C730 | C89: RICOH | E89: 自動 | G89: 5999 | H89: 5999 | K89: DR290CLBK | L89: brother ﾄﾞﾗﾑﾕﾆｯﾄ DR-290CL-BK | M89: 純正 | N89: 3890
B90: IPSIO SP ﾄﾅ- ﾏｾﾞﾝﾀ C730 | C90: RICOH | E90: 自動 | G90: 5999 | H90: 5999 | K90: DR290CLCMY | L90: brother ﾄﾞﾗﾑﾕﾆｯﾄ DR-290CL-CMY | M90: 純正 | N90: 3890
B91: IPSIO SP ﾄﾅ- ｲｴﾛ- C730 | C91: RICOH | E91: 自動 | G91: 5999 | H91: 5999 | K91: EMPTY | L91: 使用済みカートリッジ買取
B92: IPSIO SP ﾄﾅ- ﾌﾞﾗﾂｸ C730 | C92: RICOH | E92: 自動 | G92: 6336 | H92: 6336 | K92: END | L92: ※送り状に「様分」と記載をお願いします。
B93: IPSIO SP ﾄﾅ- ｼｱﾝ C730H | C93: RICOH | E93: 自動 | G93: 12778 | H93: 12778 | K93: EW-M530F | L93: EPSON ｲﾝｸｼﾞｪｯﾄ 複合機 EW-M530F
B94: IPSIO SP ﾄﾅ- ﾏｾﾞﾝﾀ C730H | C94: RICOH | E94: 自動 | G94: 12778 | H94: 12778 | K94: EW-M5610FT | L94: EPSON ｲﾝｸｼﾞｪｯﾄ 多機能ﾓﾃﾞﾙ EW-M5610FT
B95: IPSIO SP ﾄﾅ- ｲｴﾛ- C730H | C95: RICOH | E95: 自動 | G95: 12778 | H95: 12778 | K95: EW-M674FT | L95: EPSON ｲﾝｸｼﾞｪｯﾄ 複合機 EW-M674FT
B96: IPSIO SP ﾄﾅ- ﾌﾞﾗﾂｸ C730H | C96: RICOH | E96: 自動 | G96: 14049 | H96: 14049 | K96: F6U61AA | L96: HP63 ｲﾝｸｶｰﾄﾘｯｼﾞ F6U61AA ｶﾗー | M96: 純正
B97: IPSIO SP ﾄﾞﾗﾑﾕﾆﾂﾄ ｶﾗ- C730 | C97: RICOH | E97: 自動 | G97: 48703 | H97: 48703 | K97: F6U63AA | L97: HP63XL ｲﾝｸｶｰﾄﾘｯｼﾞ ｶﾗｰ(増量) F6U63AA | M97: 純正
B98: IPSIO SP ﾄﾞﾗﾑﾕﾆﾂﾄ ﾌﾞﾗﾂｸ C730 | C98: RICOH | E98: 自動 | G98: 16257 | H98: 16257 | K98: F6U64AA | L98: HP63XL ｲﾝｸｶｰﾄﾘｯｼﾞ 黒(増量) F6U64AA | M98: 純正
B99: ｲﾌﾟｼｵ SP ﾊｲﾄﾅ-ﾎﾞﾄﾙ C730 | C99: RICOH | E99: 自動 | G99: 821 | H99: 821 | K99: F9J81A | L99: HP HP729 F9J81A ﾌﾟﾘﾝﾄﾍｯﾄﾞ | M99: 純正 | N99: 47700
B100: IPSIO SP ﾄﾅ- ｼｱﾝ C710 | C100: RICOH | E100: 自動 | G100: 10579 | H100: 10579 | K100: G1330 | L100: CANON ｲﾝｸｼﾞｪｯﾄﾌﾟﾘﾝﾀｰ G1330
B101: IPSIO SP ﾄﾅ- ﾏｾﾞﾝﾀ C710 | C101: RICOH | E101: 自動 | G101: 10579 | H101: 10579 | K101: G3370 | L101: CANON ｲﾝｸｼﾞｪｯﾄ 複合機 G3370
B102: IPSIO SP ﾄﾅ- ｲｴﾛ- C710 | C102: RICOH | E102: 自動 | G102: 10579 | H102: 10579 | K102: G5030 | L102: CANON ｲﾝｸｼﾞｪｯﾄﾌﾟﾘﾝﾀｰ G5030
...
